{"dependencies":[{"name":"/home/v/dev/hwm-manager-parcel/.babelrc","includedInParent":true,"mtime":1519182498966},{"name":"/home/v/dev/hwm-manager-parcel/package.json","includedInParent":true,"mtime":1519182407146},{"name":"../../core/elements","loc":{"line":1,"column":24}},{"name":"../Title","loc":{"line":2,"column":18}},{"name":"../Button","loc":{"line":3,"column":19}},{"name":"../Input","loc":{"line":4,"column":18}},{"name":"../../stores/AlertStore","loc":{"line":6,"column":23}},{"name":"../../services/LoginService","loc":{"line":8,"column":25}},{"name":"../../services/ProfileService","loc":{"line":9,"column":27}},{"name":"../../core/router/Router","loc":{"line":11,"column":19}}],"generated":{"js":"'use strict';\n\nObject.defineProperty(exports, \"__esModule\", {\n  value: true\n});\nvar _this = undefined;\n\nvar _elements = require('../../core/elements');\n\nvar _Title = require('../Title');\n\nvar _Title2 = _interopRequireDefault(_Title);\n\nvar _Button = require('../Button');\n\nvar _Button2 = _interopRequireDefault(_Button);\n\nvar _Input = require('../Input');\n\nvar _Input2 = _interopRequireDefault(_Input);\n\nvar _AlertStore = require('../../stores/AlertStore');\n\nvar _AlertStore2 = _interopRequireDefault(_AlertStore);\n\nvar _LoginService = require('../../services/LoginService');\n\nvar _LoginService2 = _interopRequireDefault(_LoginService);\n\nvar _ProfileService = require('../../services/ProfileService');\n\nvar _ProfileService2 = _interopRequireDefault(_ProfileService);\n\nvar _Router = require('../../core/router/Router');\n\nvar _Router2 = _interopRequireDefault(_Router);\n\nfunction _interopRequireDefault(obj) { return obj && obj.__esModule ? obj : { default: obj }; }\n\nfunction _asyncToGenerator(fn) { return function () { var gen = fn.apply(this, arguments); return new Promise(function (resolve, reject) { function step(key, arg) { try { var info = gen[key](arg); var value = info.value; } catch (error) { reject(error); return; } if (info.done) { resolve(value); } else { return Promise.resolve(value).then(function (value) { step(\"next\", value); }, function (err) { step(\"throw\", err); }); } } return step(\"next\"); }); }; }\n\nconsole.log(_Router2.default);\n\nvar LoginView = function LoginView() {\n  var logIn = function () {\n    var _ref = _asyncToGenerator( /*#__PURE__*/regeneratorRuntime.mark(function _callee(event) {\n      var form, _ref2, username, password, userCreds;\n\n      return regeneratorRuntime.wrap(function _callee$(_context) {\n        while (1) {\n          switch (_context.prev = _context.next) {\n            case 0:\n              event.preventDefault();\n\n              form = event.target;\n              _ref2 = [form.elements.username.value, form.elements.password.value], username = _ref2[0], password = _ref2[1];\n              userCreds = { username: username, password: password };\n              _context.prev = 4;\n              _context.next = 7;\n              return _LoginService2.default.logIn(userCreds);\n\n            case 7:\n\n              _Router2.default.setRoute('/');\n              _context.next = 13;\n              break;\n\n            case 10:\n              _context.prev = 10;\n              _context.t0 = _context['catch'](4);\n\n              _AlertStore2.default.updateState({ toggled: true, alert: _context.t0.message });\n\n            case 13:\n              return _context.abrupt('return', false);\n\n            case 14:\n            case 'end':\n              return _context.stop();\n          }\n        }\n      }, _callee, _this, [[4, 10]]);\n    }));\n\n    return function logIn(_x) {\n      return _ref.apply(this, arguments);\n    };\n  }();\n\n  var render = function render() {\n    return (0, _elements.div)({ class: 'login-container' }, (0, _Title2.default)('Log in'), (0, _elements.form)({\n      class: 'login-form',\n      onsubmit: logIn\n    }, (0, _Input2.default)('Username', {\n      type: 'text',\n      name: 'username'\n    }), (0, _Input2.default)('Password', {\n      type: 'password',\n      name: 'password'\n    }), (0, _Button2.default)('Log me in!', {\n      type: 'submit'\n    })));\n  };\n\n  return render();\n};\n\nexports.default = LoginView;","map":{"mappings":[{"generated":{"line":8,"column":0},"source":"js/components/views/LoginView.js","original":{"line":1,"column":0}},{"generated":{"line":10,"column":0},"source":"js/components/views/LoginView.js","original":{"line":2,"column":0}},{"generated":{"line":14,"column":0},"source":"js/components/views/LoginView.js","original":{"line":3,"column":0}},{"generated":{"line":18,"column":0},"source":"js/components/views/LoginView.js","original":{"line":4,"column":0}},{"generated":{"line":22,"column":0},"source":"js/components/views/LoginView.js","original":{"line":6,"column":0}},{"generated":{"line":26,"column":0},"source":"js/components/views/LoginView.js","original":{"line":8,"column":0}},{"generated":{"line":30,"column":0},"source":"js/components/views/LoginView.js","original":{"line":9,"column":0}},{"generated":{"line":34,"column":0},"source":"js/components/views/LoginView.js","original":{"line":11,"column":0}},{"name":"console","generated":{"line":42,"column":0},"source":"js/components/views/LoginView.js","original":{"line":13,"column":0}},{"name":"log","generated":{"line":42,"column":8},"source":"js/components/views/LoginView.js","original":{"line":13,"column":8}},{"generated":{"line":42,"column":11},"source":"js/components/views/LoginView.js","original":{"line":13,"column":0}},{"generated":{"line":44,"column":0},"source":"js/components/views/LoginView.js","original":{"line":15,"column":0}},{"name":"LoginView","generated":{"line":44,"column":4},"source":"js/components/views/LoginView.js","original":{"line":15,"column":6}},{"generated":{"line":44,"column":16},"source":"js/components/views/LoginView.js","original":{"line":15,"column":18}},{"name":"LoginView","generated":{"line":44,"column":25},"source":"js/components/views/LoginView.js","original":{"line":15,"column":6}},{"generated":{"line":44,"column":34},"source":"js/components/views/LoginView.js","original":{"line":15,"column":18}},{"generated":{"line":44,"column":37},"source":"js/components/views/LoginView.js","original":{"line":15,"column":24}},{"generated":{"line":45,"column":0},"source":"js/components/views/LoginView.js","original":{"line":16,"column":2}},{"name":"logIn","generated":{"line":45,"column":6},"source":"js/components/views/LoginView.js","original":{"line":16,"column":8}},{"generated":{"line":46,"column":0},"source":"js/components/views/LoginView.js","original":{"line":16,"column":8}},{"generated":{"line":46,"column":71},"source":"js/components/views/LoginView.js","original":{"line":16,"column":16}},{"name":"event","generated":{"line":46,"column":88},"source":"js/components/views/LoginView.js","original":{"line":16,"column":22}},{"generated":{"line":46,"column":93},"source":"js/components/views/LoginView.js","original":{"line":16,"column":16}},{"generated":{"line":47,"column":0},"source":"js/components/views/LoginView.js","original":{"line":16,"column":16}},{"generated":{"line":49,"column":0},"source":"js/components/views/LoginView.js","original":{"line":16,"column":16}},{"generated":{"line":50,"column":0},"source":"js/components/views/LoginView.js","original":{"line":16,"column":16}},{"generated":{"line":51,"column":0},"source":"js/components/views/LoginView.js","original":{"line":16,"column":16}},{"generated":{"line":52,"column":0},"source":"js/components/views/LoginView.js","original":{"line":16,"column":16}},{"name":"event","generated":{"line":53,"column":0},"source":"js/components/views/LoginView.js","original":{"line":17,"column":4}},{"name":"preventDefault","generated":{"line":53,"column":20},"source":"js/components/views/LoginView.js","original":{"line":17,"column":10}},{"generated":{"line":53,"column":34},"source":"js/components/views/LoginView.js","original":{"line":17,"column":4}},{"name":"form","generated":{"line":55,"column":0},"source":"js/components/views/LoginView.js","original":{"line":19,"column":10}},{"generated":{"line":55,"column":18},"source":"js/components/views/LoginView.js","original":{"line":16,"column":16}},{"name":"event","generated":{"line":55,"column":21},"source":"js/components/views/LoginView.js","original":{"line":19,"column":17}},{"name":"target","generated":{"line":55,"column":27},"source":"js/components/views/LoginView.js","original":{"line":19,"column":23}},{"generated":{"line":55,"column":33},"source":"js/components/views/LoginView.js","original":{"line":16,"column":16}},{"generated":{"line":56,"column":0},"source":"js/components/views/LoginView.js","original":{"line":16,"column":16}},{"generated":{"line":56,"column":22},"source":"js/components/views/LoginView.js","original":{"line":21,"column":33}},{"name":"form","generated":{"line":56,"column":23},"source":"js/components/views/LoginView.js","original":{"line":22,"column":6}},{"name":"elements","generated":{"line":56,"column":28},"source":"js/components/views/LoginView.js","original":{"line":22,"column":11}},{"generated":{"line":56,"column":36},"source":"js/components/views/LoginView.js","original":{"line":22,"column":6}},{"name":"username","generated":{"line":56,"column":37},"source":"js/components/views/LoginView.js","original":{"line":22,"column":20}},{"generated":{"line":56,"column":45},"source":"js/components/views/LoginView.js","original":{"line":22,"column":6}},{"name":"value","generated":{"line":56,"column":46},"source":"js/components/views/LoginView.js","original":{"line":22,"column":29}},{"generated":{"line":56,"column":51},"source":"js/components/views/LoginView.js","original":{"line":21,"column":33}},{"name":"form","generated":{"line":56,"column":53},"source":"js/components/views/LoginView.js","original":{"line":23,"column":6}},{"name":"elements","generated":{"line":56,"column":58},"source":"js/components/views/LoginView.js","original":{"line":23,"column":11}},{"generated":{"line":56,"column":66},"source":"js/components/views/LoginView.js","original":{"line":23,"column":6}},{"name":"password","generated":{"line":56,"column":67},"source":"js/components/views/LoginView.js","original":{"line":23,"column":20}},{"generated":{"line":56,"column":75},"source":"js/components/views/LoginView.js","original":{"line":23,"column":6}},{"name":"value","generated":{"line":56,"column":76},"source":"js/components/views/LoginView.js","original":{"line":23,"column":29}},{"generated":{"line":56,"column":81},"source":"js/components/views/LoginView.js","original":{"line":21,"column":33}},{"generated":{"line":56,"column":82},"source":"js/components/views/LoginView.js","original":{"line":16,"column":16}},{"name":"username","generated":{"line":56,"column":84},"source":"js/components/views/LoginView.js","original":{"line":21,"column":11}},{"generated":{"line":56,"column":92},"source":"js/components/views/LoginView.js","original":{"line":16,"column":16}},{"name":"password","generated":{"line":56,"column":105},"source":"js/components/views/LoginView.js","original":{"line":21,"column":21}},{"generated":{"line":56,"column":113},"source":"js/components/views/LoginView.js","original":{"line":16,"column":16}},{"name":"userCreds","generated":{"line":57,"column":0},"source":"js/components/views/LoginView.js","original":{"line":26,"column":10}},{"generated":{"line":57,"column":23},"source":"js/components/views/LoginView.js","original":{"line":16,"column":16}},{"generated":{"line":57,"column":26},"source":"js/components/views/LoginView.js","original":{"line":26,"column":22}},{"name":"username","generated":{"line":57,"column":28},"source":"js/components/views/LoginView.js","original":{"line":26,"column":23}},{"generated":{"line":57,"column":46},"source":"js/components/views/LoginView.js","original":{"line":26,"column":22}},{"name":"password","generated":{"line":57,"column":48},"source":"js/components/views/LoginView.js","original":{"line":26,"column":33}},{"generated":{"line":57,"column":66},"source":"js/components/views/LoginView.js","original":{"line":26,"column":22}},{"generated":{"line":57,"column":68},"source":"js/components/views/LoginView.js","original":{"line":16,"column":16}},{"generated":{"line":58,"column":0},"source":"js/components/views/LoginView.js","original":{"line":16,"column":16}},{"generated":{"line":59,"column":0},"source":"js/components/views/LoginView.js","original":{"line":16,"column":16}},{"generated":{"line":60,"column":0},"source":"js/components/views/LoginView.js","original":{"line":16,"column":16}},{"generated":{"line":60,"column":21},"source":"js/components/views/LoginView.js","original":{"line":29,"column":12}},{"name":"logIn","generated":{"line":60,"column":44},"source":"js/components/views/LoginView.js","original":{"line":29,"column":25}},{"generated":{"line":60,"column":49},"source":"js/components/views/LoginView.js","original":{"line":29,"column":12}},{"name":"userCreds","generated":{"line":60,"column":50},"source":"js/components/views/LoginView.js","original":{"line":29,"column":31}},{"generated":{"line":60,"column":59},"source":"js/components/views/LoginView.js","original":{"line":29,"column":12}},{"generated":{"line":60,"column":60},"source":"js/components/views/LoginView.js","original":{"line":16,"column":16}},{"generated":{"line":62,"column":0},"source":"js/components/views/LoginView.js","original":{"line":16,"column":16}},{"generated":{"line":64,"column":0},"source":"js/components/views/LoginView.js","original":{"line":31,"column":6}},{"name":"setRoute","generated":{"line":64,"column":31},"source":"js/components/views/LoginView.js","original":{"line":31,"column":13}},{"generated":{"line":64,"column":39},"source":"js/components/views/LoginView.js","original":{"line":31,"column":6}},{"generated":{"line":64,"column":40},"source":"js/components/views/LoginView.js","original":{"line":31,"column":22}},{"generated":{"line":64,"column":43},"source":"js/components/views/LoginView.js","original":{"line":31,"column":6}},{"generated":{"line":65,"column":0},"source":"js/components/views/LoginView.js","original":{"line":16,"column":16}},{"generated":{"line":66,"column":0},"source":"js/components/views/LoginView.js","original":{"line":16,"column":16}},{"generated":{"line":68,"column":0},"source":"js/components/views/LoginView.js","original":{"line":16,"column":16}},{"generated":{"line":69,"column":0},"source":"js/components/views/LoginView.js","original":{"line":16,"column":16}},{"generated":{"line":70,"column":0},"source":"js/components/views/LoginView.js","original":{"line":16,"column":16}},{"generated":{"line":72,"column":0},"source":"js/components/views/LoginView.js","original":{"line":33,"column":6}},{"name":"updateState","generated":{"line":72,"column":35},"source":"js/components/views/LoginView.js","original":{"line":33,"column":17}},{"generated":{"line":72,"column":46},"source":"js/components/views/LoginView.js","original":{"line":33,"column":6}},{"generated":{"line":72,"column":47},"source":"js/components/views/LoginView.js","original":{"line":33,"column":29}},{"name":"toggled","generated":{"line":72,"column":49},"source":"js/components/views/LoginView.js","original":{"line":33,"column":30}},{"generated":{"line":72,"column":58},"source":"js/components/views/LoginView.js","original":{"line":33,"column":39}},{"generated":{"line":72,"column":62},"source":"js/components/views/LoginView.js","original":{"line":33,"column":29}},{"name":"alert","generated":{"line":72,"column":64},"source":"js/components/views/LoginView.js","original":{"line":33,"column":45}},{"generated":{"line":72,"column":71},"source":"js/components/views/LoginView.js","original":{"line":33,"column":52}},{"name":"message","generated":{"line":72,"column":83},"source":"js/components/views/LoginView.js","original":{"line":33,"column":58}},{"generated":{"line":72,"column":90},"source":"js/components/views/LoginView.js","original":{"line":33,"column":29}},{"generated":{"line":72,"column":92},"source":"js/components/views/LoginView.js","original":{"line":33,"column":6}},{"generated":{"line":74,"column":0},"source":"js/components/views/LoginView.js","original":{"line":16,"column":16}},{"generated":{"line":75,"column":0},"source":"js/components/views/LoginView.js","original":{"line":16,"column":16}},{"generated":{"line":75,"column":47},"source":"js/components/views/LoginView.js","original":{"line":36,"column":11}},{"generated":{"line":75,"column":52},"source":"js/components/views/LoginView.js","original":{"line":16,"column":16}},{"generated":{"line":77,"column":0},"source":"js/components/views/LoginView.js","original":{"line":16,"column":16}},{"generated":{"line":78,"column":0},"source":"js/components/views/LoginView.js","original":{"line":16,"column":16}},{"generated":{"line":79,"column":0},"source":"js/components/views/LoginView.js","original":{"line":16,"column":16}},{"generated":{"line":80,"column":0},"source":"js/components/views/LoginView.js","original":{"line":16,"column":16}},{"generated":{"line":81,"column":0},"source":"js/components/views/LoginView.js","original":{"line":16,"column":16}},{"generated":{"line":82,"column":0},"source":"js/components/views/LoginView.js","original":{"line":16,"column":16}},{"generated":{"line":83,"column":0},"source":"js/components/views/LoginView.js","original":{"line":16,"column":16}},{"generated":{"line":83,"column":5},"source":"js/components/views/LoginView.js","original":{"line":16,"column":8}},{"generated":{"line":85,"column":0},"source":"js/components/views/LoginView.js","original":{"line":16,"column":8}},{"generated":{"line":86,"column":0},"source":"js/components/views/LoginView.js","original":{"line":16,"column":8}},{"generated":{"line":87,"column":0},"source":"js/components/views/LoginView.js","original":{"line":16,"column":8}},{"generated":{"line":88,"column":0},"source":"js/components/views/LoginView.js","original":{"line":16,"column":8}},{"generated":{"line":88,"column":5},"source":"js/components/views/LoginView.js","original":{"line":16,"column":2}},{"generated":{"line":90,"column":0},"source":"js/components/views/LoginView.js","original":{"line":39,"column":2}},{"name":"render","generated":{"line":90,"column":6},"source":"js/components/views/LoginView.js","original":{"line":39,"column":8}},{"generated":{"line":90,"column":15},"source":"js/components/views/LoginView.js","original":{"line":39,"column":17}},{"name":"render","generated":{"line":90,"column":24},"source":"js/components/views/LoginView.js","original":{"line":39,"column":8}},{"generated":{"line":90,"column":30},"source":"js/components/views/LoginView.js","original":{"line":39,"column":17}},{"generated":{"line":90,"column":33},"source":"js/components/views/LoginView.js","original":{"line":39,"column":23}},{"generated":{"line":91,"column":0},"source":"js/components/views/LoginView.js","original":{"line":40,"column":4}},{"generated":{"line":91,"column":11},"source":"js/components/views/LoginView.js","original":{"line":40,"column":11}},{"generated":{"line":91,"column":30},"source":"js/components/views/LoginView.js","original":{"line":41,"column":6}},{"name":"class","generated":{"line":91,"column":32},"source":"js/components/views/LoginView.js","original":{"line":41,"column":7}},{"generated":{"line":91,"column":39},"source":"js/components/views/LoginView.js","original":{"line":41,"column":14}},{"generated":{"line":91,"column":56},"source":"js/components/views/LoginView.js","original":{"line":41,"column":6}},{"generated":{"line":91,"column":58},"source":"js/components/views/LoginView.js","original":{"line":40,"column":11}},{"generated":{"line":91,"column":60},"source":"js/components/views/LoginView.js","original":{"line":42,"column":6}},{"generated":{"line":91,"column":81},"source":"js/components/views/LoginView.js","original":{"line":42,"column":12}},{"generated":{"line":91,"column":89},"source":"js/components/views/LoginView.js","original":{"line":42,"column":6}},{"generated":{"line":91,"column":90},"source":"js/components/views/LoginView.js","original":{"line":40,"column":11}},{"generated":{"line":91,"column":92},"source":"js/components/views/LoginView.js","original":{"line":43,"column":6}},{"generated":{"line":91,"column":112},"source":"js/components/views/LoginView.js","original":{"line":43,"column":11}},{"name":"class","generated":{"line":92,"column":0},"source":"js/components/views/LoginView.js","original":{"line":44,"column":10}},{"generated":{"line":92,"column":13},"source":"js/components/views/LoginView.js","original":{"line":44,"column":17}},{"generated":{"line":92,"column":25},"source":"js/components/views/LoginView.js","original":{"line":43,"column":11}},{"name":"onsubmit","generated":{"line":93,"column":0},"source":"js/components/views/LoginView.js","original":{"line":45,"column":10}},{"name":"logIn","generated":{"line":93,"column":16},"source":"js/components/views/LoginView.js","original":{"line":45,"column":20}},{"generated":{"line":94,"column":0},"source":"js/components/views/LoginView.js","original":{"line":43,"column":11}},{"generated":{"line":94,"column":5},"source":"js/components/views/LoginView.js","original":{"line":43,"column":6}},{"generated":{"line":94,"column":7},"source":"js/components/views/LoginView.js","original":{"line":47,"column":8}},{"generated":{"line":94,"column":28},"source":"js/components/views/LoginView.js","original":{"line":47,"column":14}},{"generated":{"line":94,"column":38},"source":"js/components/views/LoginView.js","original":{"line":47,"column":8}},{"generated":{"line":94,"column":40},"source":"js/components/views/LoginView.js","original":{"line":47,"column":26}},{"name":"type","generated":{"line":95,"column":0},"source":"js/components/views/LoginView.js","original":{"line":48,"column":10}},{"generated":{"line":95,"column":12},"source":"js/components/views/LoginView.js","original":{"line":48,"column":16}},{"generated":{"line":95,"column":18},"source":"js/components/views/LoginView.js","original":{"line":47,"column":26}},{"name":"name","generated":{"line":96,"column":0},"source":"js/components/views/LoginView.js","original":{"line":49,"column":10}},{"generated":{"line":96,"column":12},"source":"js/components/views/LoginView.js","original":{"line":49,"column":16}},{"generated":{"line":97,"column":0},"source":"js/components/views/LoginView.js","original":{"line":47,"column":26}},{"generated":{"line":97,"column":5},"source":"js/components/views/LoginView.js","original":{"line":47,"column":8}},{"generated":{"line":97,"column":6},"source":"js/components/views/LoginView.js","original":{"line":43,"column":6}},{"generated":{"line":97,"column":8},"source":"js/components/views/LoginView.js","original":{"line":51,"column":8}},{"generated":{"line":97,"column":29},"source":"js/components/views/LoginView.js","original":{"line":51,"column":14}},{"generated":{"line":97,"column":39},"source":"js/components/views/LoginView.js","original":{"line":51,"column":8}},{"generated":{"line":97,"column":41},"source":"js/components/views/LoginView.js","original":{"line":51,"column":26}},{"name":"type","generated":{"line":98,"column":0},"source":"js/components/views/LoginView.js","original":{"line":52,"column":10}},{"generated":{"line":98,"column":12},"source":"js/components/views/LoginView.js","original":{"line":52,"column":16}},{"generated":{"line":98,"column":22},"source":"js/components/views/LoginView.js","original":{"line":51,"column":26}},{"name":"name","generated":{"line":99,"column":0},"source":"js/components/views/LoginView.js","original":{"line":53,"column":10}},{"generated":{"line":99,"column":12},"source":"js/components/views/LoginView.js","original":{"line":53,"column":16}},{"generated":{"line":100,"column":0},"source":"js/components/views/LoginView.js","original":{"line":51,"column":26}},{"generated":{"line":100,"column":5},"source":"js/components/views/LoginView.js","original":{"line":51,"column":8}},{"generated":{"line":100,"column":6},"source":"js/components/views/LoginView.js","original":{"line":43,"column":6}},{"generated":{"line":100,"column":8},"source":"js/components/views/LoginView.js","original":{"line":55,"column":8}},{"generated":{"line":100,"column":30},"source":"js/components/views/LoginView.js","original":{"line":55,"column":15}},{"generated":{"line":100,"column":42},"source":"js/components/views/LoginView.js","original":{"line":55,"column":8}},{"generated":{"line":100,"column":44},"source":"js/components/views/LoginView.js","original":{"line":55,"column":29}},{"name":"type","generated":{"line":101,"column":0},"source":"js/components/views/LoginView.js","original":{"line":56,"column":10}},{"generated":{"line":101,"column":12},"source":"js/components/views/LoginView.js","original":{"line":56,"column":16}},{"generated":{"line":102,"column":0},"source":"js/components/views/LoginView.js","original":{"line":55,"column":29}},{"generated":{"line":102,"column":5},"source":"js/components/views/LoginView.js","original":{"line":55,"column":8}},{"generated":{"line":102,"column":6},"source":"js/components/views/LoginView.js","original":{"line":43,"column":6}},{"generated":{"line":102,"column":7},"source":"js/components/views/LoginView.js","original":{"line":40,"column":11}},{"generated":{"line":102,"column":8},"source":"js/components/views/LoginView.js","original":{"line":40,"column":4}},{"generated":{"line":103,"column":0},"source":"js/components/views/LoginView.js","original":{"line":60,"column":3}},{"generated":{"line":103,"column":3},"source":"js/components/views/LoginView.js","original":{"line":39,"column":2}},{"generated":{"line":105,"column":0},"source":"js/components/views/LoginView.js","original":{"line":62,"column":2}},{"name":"render","generated":{"line":105,"column":9},"source":"js/components/views/LoginView.js","original":{"line":62,"column":9}},{"generated":{"line":105,"column":17},"source":"js/components/views/LoginView.js","original":{"line":62,"column":2}},{"generated":{"line":106,"column":0},"source":"js/components/views/LoginView.js","original":{"line":63,"column":1}},{"generated":{"line":106,"column":1},"source":"js/components/views/LoginView.js","original":{"line":15,"column":0}},{"name":"LoginView","generated":{"line":108,"column":18},"source":"js/components/views/LoginView.js","original":{"line":65,"column":15}}],"sources":{"js/components/views/LoginView.js":"import {div, form} from '../../core/elements'\nimport Title from '../Title'\nimport Button from '../Button'\nimport Input from '../Input'\n\nimport alertStore from '../../stores/AlertStore'\n\nimport loginService from '../../services/LoginService'\nimport profileService from '../../services/ProfileService'\n\nimport router from '../../core/router/Router'\n\nconsole.log(router)\n\nconst LoginView = () => {\n  const logIn = async event => {\n    event.preventDefault()\n\n    const form = event.target\n\n    const [username, password] = [\n      form.elements.username.value,\n      form.elements.password.value\n    ]\n\n    const userCreds = {username, password}\n\n    try {\n      await loginService.logIn(userCreds)\n\n      router.setRoute('/')\n    } catch (error) {\n      alertStore.updateState({toggled: true, alert: error.message})\n    }\n\n    return false\n  }\n\n  const render = () => {\n    return div(\n      {class: 'login-container'},\n      Title('Log in'),\n      form({\n          class: 'login-form',\n          onsubmit: logIn\n        },\n        Input('Username', {\n          type: 'text',\n          name: 'username',\n        }),\n        Input('Password', {\n          type: 'password',\n          name: 'password'\n        }),\n        Button('Log me in!', {\n          type: 'submit'\n        })\n      )\n    )\n  }\n\n  return render()\n}\n\nexport default LoginView\n"},"lineCount":null}},"hash":"1acd62158caa85eb9e5d135fb7a758c8","cacheData":{"env":{}}}